libpasteurize/__init__.py
libpasteurize/main.py
libpasteurize/fixes/__init__.py
libpasteurize/fixes/feature_base.py
libpasteurize/fixes/fix_add_all__future__imports.py
libpasteurize/fixes/fix_add_all_future_builtins.py
libpasteurize/fixes/fix_add_future_standard_library_import.py
libpasteurize/fixes/fix_annotations.py
libpasteurize/fixes/fix_division.py
libpasteurize/fixes/fix_features.py
libpasteurize/fixes/fix_fullargspec.py
libpasteurize/fixes/fix_future_builtins.py
libpasteurize/fixes/fix_getcwd.py
libpasteurize/fixes/fix_imports.py
libpasteurize/fixes/fix_imports2.py
libpasteurize/fixes/fix_kwargs.py
libpasteurize/fixes/fix_memoryview.py
libpasteurize/fixes/fix_metaclass.py
libpasteurize/fixes/fix_newstyle.py
libpasteurize/fixes/fix_next.py
libpasteurize/fixes/fix_printfunction.py
libpasteurize/fixes/fix_raise.py
libpasteurize/fixes/fix_raise_.py
libpasteurize/fixes/fix_throw.py
libpasteurize/fixes/fix_unpacking.py
libtridens-0.0.1.dist-info/LICENSE.txt
libtridens-0.0.1.dist-info/METADATA
libtridens-0.0.1.dist-info/WHEEL
libtridens-0.0.1.dist-info/entry_points.txt
libtridens-0.0.1.dist-info/top_level.txt
libtridens-0.0.1.dist-info/RECORD
